dictator/dot_dict.cp312-win_amd64.pyd
DataChanger-0.1.4.dist-info/LICENSE
DataChanger-0.1.4.dist-info/METADATA
DataChanger-0.1.4.dist-info/WHEEL
DataChanger-0.1.4.dist-info/top_level.txt
DataChanger-0.1.4.dist-info/RECORD
