Metadata-Version: 2.1
Name: DataChanger
Version: 0.1.4
Summary: A class for dot notation access to dictionaries
Author: Adarsh Dhiman
Author-email: adarshdhiman007@gmail.com
Requires-Python: >=3.6
License-File: LICENSE
Requires-Dist: Cython
